[{"first":"Aisha","last":"Swift","email":"greenwolf04@gmail.com","address":"71183 Turner Extensions","created":"September 6, 2017","balance":"$7,223.08"},{"first":"Adrien","last":"Kuhlman","email":"orchidwolf10@gmail.com","address":"65265 King Well","created":"June 10, 2016","balance":"$2,760.95"},{"first":"Elisa","last":"Dietrich","email":"fuchsiasquirrel05@gmail.com","address":"5754 Shanahan Mills","created":"December 9, 2012","balance":"$2,148.70"},{"first":"Breanne","last":"Lueilwitz","email":"Breanne.Lueilwitz@loyce.net","address":"4561 MacGyver Lane","created":"August 9, 2013","balance":"$6,255.62"},{"first":"Shana","last":"Toy","email":"skyblueturtle81@gmail.com","address":"925 Stoltenberg Islands","created":"December 21, 2016","balance":"$3,019.11"},{"first":"Lelia","last":"Mante","email":"limegiraffe88@gmail.com","address":"1464 Marco Coves","created":"June 22, 2010","balance":"$6,831.92"},{"first":"Noel","last":"Bauch","email":"Noel.Bauch@samir.biz","address":"504 Fisher Walks","created":"July 19, 2016","balance":"$4,376.79"},{"first":"Mozelle","last":"Hermiston","email":"mintgreensquirrel41@gmail.com","address":"45906 Russel Prairie","created":"August 22, 2018","balance":"$7,314.14"},{"first":"Lincoln","last":"Jerde","email":"Lincoln.Jerde@nat.name","address":"21246 Simonis Lock","created":"February 12, 2017","balance":"$8,314.57"},{"first":"Emerald","last":"Gislason","email":"mintgreengiraffe95@gmail.com","address":"7236 Walter Walk","created":"November 25, 2010","balance":"$4,852.37"},{"first":"Bailee","last":"Sauer","email":"purpleturtle13@gmail.com","address":"392 Stiedemann Ridges","created":"December 30, 2017","balance":"$6,267.27"},{"first":"Horace","last":"Mraz","email":"Horace.Mraz@elody.org","address":"93158 Torphy Falls","created":"October 11, 2013","balance":"$3,458.28"},{"first":"Gracie","last":"Roberts","email":"fuchsiagiraffe71@gmail.com","address":"1345 Braxton Corners","created":"May 21, 2018","balance":"$2,545.24"},{"first":"Lorenzo","last":"Kihn","email":"Lorenzo.Kihn@cesar.net","address":"9922 Johns Alley","created":"December 5, 2017","balance":"$5,644.25"},{"first":"Jerel","last":"Mills","email":"Jerel.Mills@tomasa.biz","address":"1058 Keebler Rest","created":"April 12, 2014","balance":"$5,568.25"},{"first":"Mack","last":"Waters","email":"mintgreenwolf64@gmail.com","address":"505 Runolfsdottir Course","created":"July 21, 2017","balance":"$5,337.23"},{"first":"Hope","last":"Bins","email":"Hope.Bins@erich.info","address":"0621 Gottlieb Neck","created":"August 28, 2014","balance":"$3,726.38"},{"first":"Brooke","last":"White","email":"blacksquirrel53@gmail.com","address":"096 Darien Isle","created":"July 8, 2012","balance":"$1,871.39"},{"first":"Candido","last":"Abernathy","email":"Candido.Abernathy@deondre.com","address":"59672 Shayna Springs","created":"September 16, 2012","balance":"$4,129.05"},{"first":"Wilford","last":"Flatley","email":"greengiraffe41@gmail.com","address":"45033 Mia Garden","created":"June 2, 2014","balance":"$4,474.99"},{"first":"Elliott","last":"Ratke","email":"whiterabbit02@gmail.com","address":"181 Molly Ramp","created":"April 26, 2015","balance":"$6,806.07"},{"first":"Garrett","last":"Terry","email":"Garrett.Terry@jaydon.biz","address":"73698 Alexandrea Track","created":"November 22, 2016","balance":"$2,298.79"},{"first":"Jaida","last":"Blanda","email":"Jaida.Blanda@kennedy.info","address":"156 Adam Run","created":"January 24, 2011","balance":"$1,726.61"},{"first":"Lon","last":"Brekke","email":"Lon.Brekke@emmett.info","address":"37154 Catherine Ridge","created":"May 8, 2014","balance":"$5,727.04"},{"first":"Marshall","last":"Predovic","email":"blacksquirrel26@gmail.com","address":"809 Quinn Unions","created":"February 24, 2017","balance":"$711.91"},{"first":"Hayden","last":"Dickens","email":"Hayden.Dickens@geovanny.biz","address":"5690 Agnes Harbor","created":"July 6, 2016","balance":"$9,222.05"},{"first":"Cade","last":"Botsford","email":"Cade.Botsford@leila.name","address":"299 Lurline Forges","created":"June 6, 2010","balance":"$1,374.21"},{"first":"Earl","last":"Davis","email":"Earl.Davis@marianna.net","address":"3331 Violet Ways","created":"June 28, 2017","balance":"$2,691.61"},{"first":"Keagan","last":"Ziemann","email":"Keagan.Ziemann@hester.biz","address":"876 Upton Rest","created":"June 20, 2018","balance":"$4,300.57"},{"first":"Adelia","last":"Bosco","email":"greensquirrel05@gmail.com","address":"78850 Destini Roads","created":"December 8, 2015","balance":"$7,482.28"},{"first":"Sonny","last":"Pacocha","email":"pinkturtle76@gmail.com","address":"946 Emanuel Viaduct","created":"May 21, 2017","balance":"$3,363.10"},{"first":"Quinton","last":"Hamill","email":"Quinton.Hamill@eduardo.org","address":"29109 Rene Knoll","created":"April 25, 2013","balance":"$7,732.77"},{"first":"Cheyanne","last":"Cormier","email":"lavendergiraffe01@gmail.com","address":"14414 Lavern Burgs","created":"November 10, 2014","balance":"$7,160.86"},{"first":"Holly","last":"Larson","email":"maroonturtle44@gmail.com","address":"77799 Maybell Landing","created":"September 28, 2013","balance":"$5,022.23"},{"first":"Caitlyn","last":"Jaskolski","email":"Caitlyn.Jaskolski@reyes.name","address":"70933 Jayda Place","created":"October 6, 2017","balance":"$8,251.97"},{"first":"Jamarcus","last":"Reinger","email":"orchidrabbit46@gmail.com","address":"4670 Lamar Ferry","created":"August 7, 2018","balance":"$6,035.68"},{"first":"Katharina","last":"Schaden","email":"limegiraffe29@gmail.com","address":"500 Lacy Roads","created":"March 20, 2014","balance":"$5,222.13"},{"first":"Daniella","last":"Friesen","email":"Daniella.Friesen@damon.biz","address":"4317 Keanu Mews","created":"December 16, 2012","balance":"$7,343.76"},{"first":"Verlie","last":"Gottlieb","email":"tanfrog28@gmail.com","address":"439 Johnpaul Mission","created":"June 17, 2015","balance":"$1,823.37"},{"first":"Vicenta","last":"Jacobson","email":"Vicenta.Jacobson@meaghan.net","address":"6976 Ritchie Forest","created":"November 14, 2013","balance":"$4,284.26"},{"first":"Curt","last":"Walsh","email":"greenturtle62@gmail.com","address":"2988 Cummerata Lake","created":"November 8, 2018","balance":"$4,708.61"},{"first":"Brent","last":"Wintheiser","email":"Brent.Wintheiser@novella.com","address":"94343 Reva Bypass","created":"March 26, 2011","balance":"$7,538.38"},{"first":"Hilma","last":"Sporer","email":"orangesquirrel93@gmail.com","address":"74477 Carter Key","created":"March 2, 2019","balance":"$8,392.44"},{"first":"Ulices","last":"Abernathy","email":"yellowsquirrel63@gmail.com","address":"4041 Fermin Crossroad","created":"May 7, 2013","balance":"$3,297.99"},{"first":"Eusebio","last":"Welch","email":"Eusebio.Welch@sven.biz","address":"171 Lesch Freeway","created":"August 25, 2013","balance":"$3,469.86"},{"first":"Presley","last":"Erdman","email":"Presley.Erdman@german.info","address":"5606 Brendan Drives","created":"August 25, 2014","balance":"$7,259.38"},{"first":"Jadon","last":"Lynch","email":"Jadon.Lynch@arnold.biz","address":"224 Bogisich Mount","created":"March 18, 2010","balance":"$1,237.32"},{"first":"Ben","last":"Balistreri","email":"fuchsiarabbit49@gmail.com","address":"1609 Roscoe Road","created":"January 28, 2014","balance":"$2,059.12"},{"first":"Kellie","last":"Sanford","email":"Kellie.Sanford@freeda.net","address":"19470 Ora Manors","created":"May 6, 2019","balance":"$3,831.36"},{"first":"Arch","last":"Dach","email":"azurerabbit87@gmail.com","address":"64742 Rau Falls","created":"February 25, 2011","balance":"$4,312.46"},{"first":"Cristobal","last":"Auer","email":"Cristobal.Auer@cassie.biz","address":"02568 Dedric Underpass","created":"November 25, 2011","balance":"$2,482.78"},{"first":"Agustina","last":"Purdy","email":"Agustina.Purdy@hal.biz","address":"798 Charles Mews","created":"March 31, 2013","balance":"$7,637.25"},{"first":"Johnathon","last":"Bergnaum","email":"Johnathon.Bergnaum@sandy.org","address":"7587 Cummings River","created":"July 22, 2010","balance":"$9,881.10"},{"first":"Dora","last":"Dibbert","email":"Dora.Dibbert@mekhi.org","address":"27850 Herman Square","created":"January 19, 2019","balance":"$1,032.06"},{"first":"Glenna","last":"Parisian","email":"Glenna.Parisian@justus.net","address":"1068 Rippin Falls","created":"April 29, 2018","balance":"$3,159.97"},{"first":"Scot","last":"Hudson","email":"Scot.Hudson@dariana.info","address":"86467 Osinski Prairie","created":"November 5, 2009","balance":"$2,315.21"},{"first":"Halle","last":"Howell","email":"turquoiseturtle26@gmail.com","address":"3247 Steve Ferry","created":"February 20, 2019","balance":"$4,641.23"},{"first":"Casper","last":"Dickens","email":"Casper.Dickens@juliana.info","address":"9482 Davis Circle","created":"December 5, 2009","balance":"$6,223.84"},{"first":"Henriette","last":"Auer","email":"bluegiraffe28@gmail.com","address":"2543 Ebert Points","created":"March 20, 2013","balance":"$1,011.31"},{"first":"Wilhelmine","last":"Orn","email":"greenwolf45@gmail.com","address":"05551 Durgan Drives","created":"May 22, 2011","balance":"$5,986.32"},{"first":"Wilton","last":"Windler","email":"Wilton.Windler@florida.net","address":"421 Cecile Spurs","created":"February 2, 2011","balance":"$4,721.85"},{"first":"Arianna","last":"Williamson","email":"mintgreenfrog64@gmail.com","address":"320 Nelson Causeway","created":"August 28, 2011","balance":"$8,893.80"},{"first":"Danielle","last":"Rohan","email":"tangiraffe15@gmail.com","address":"5247 Justina Drive","created":"February 2, 2013","balance":"$7,679.21"},{"first":"Koby","last":"Ritchie","email":"fuchsiarabbit85@gmail.com","address":"31678 Yost Fort","created":"April 1, 2016","balance":"$2,834.03"},{"first":"Mckayla","last":"Ullrich","email":"Mckayla.Ullrich@breanna.org","address":"0182 Broderick Lane","created":"September 5, 2014","balance":"$6,991.57"},{"first":"Rogelio","last":"Vandervort","email":"Rogelio.Vandervort@marcus.com","address":"56228 Gregg Fall","created":"September 17, 2016","balance":"$5,964.80"},{"first":"Reinhold","last":"Miller","email":"tanfrog00@gmail.com","address":"595 Dino Ranch","created":"July 10, 2012","balance":"$7,882.09"},{"first":"Stacey","last":"Goldner","email":"Stacey.Goldner@mina.name","address":"0908 Schumm Lake","created":"April 17, 2018","balance":"$8,155.53"},{"first":"Zakary","last":"Daniel","email":"violetsquirrel71@gmail.com","address":"41118 Bogan Vista","created":"April 28, 2012","balance":"$7,926.15"},{"first":"Omari","last":"Maggio","email":"Omari.Maggio@melissa.org","address":"30641 Heloise Crossroad","created":"November 29, 2017","balance":"$6,138.94"},{"first":"Monserrate","last":"Kessler","email":"olivesquirrel55@gmail.com","address":"4679 Parisian Route","created":"March 8, 2013","balance":"$5,720.51"},{"first":"Sarina","last":"Hintz","email":"Sarina.Hintz@taryn.org","address":"19404 McDermott Ridge","created":"April 27, 2014","balance":"$3,863.72"},{"first":"Lesley","last":"Mohr","email":"maroongiraffe82@gmail.com","address":"85700 Don Island","created":"May 9, 2015","balance":"$5,164.08"},{"first":"Clemens","last":"Marks","email":"azurefrog08@gmail.com","address":"102 Eldora Estate","created":"February 19, 2010","balance":"$8,620.44"},{"first":"Sincere","last":"Bartoletti","email":"Sincere.Bartoletti@alford.biz","address":"7523 Pouros Coves","created":"March 18, 2015","balance":"$988.86"}]